{
  "info":[
    {
      "id" : 0,
      "name": "First post!",
      "surname" : "My first content!",
      "info" : "My first content!"
    },
    {
      "id" : 1,s
      "name": "Siarhei",
      "surname" : "Rachytski",
      "info" : "It's me"
    },
    {
      "id" : 2,
      "name": "Aleksei",
      "surname" : "Korsak",
      "info" : "My teammate"
    },
    {
      "id" : 3,
      "name": "Ihar and Volha",
      "surname" : "Rachytskiye",
      "info" : "My family"
    },
    {
      "id" : 4,
      "name": "Rait",
      "surname" : "",
      "info" : "My dog"
    }
  ]
}